MANIFEST.in
README.rst
setup.cfg
setup.py
meow/__init__.py
meow/_version.py
meow/cmdline.py
meow/markdown.py
meow/meow.py
meow/rst.py
meow/server.py
meow/txtile.py
meow.egg-info/PKG-INFO
meow.egg-info/SOURCES.txt
meow.egg-info/dependency_links.txt
meow.egg-info/entry_points.txt
meow.egg-info/not-zip-safe
meow.egg-info/requires.txt
meow.egg-info/top_level.txt
meow/static/app.js
meow/static/app.min.js
meow/static/ender.js
meow/static/ender.min.js
meow/static/github-dirty-shade.png
meow/static/github-status.png
meow/static/github.css
meow/static/github.min.css
meow/templates/github-export.tpl
meow/templates/github.tpl