Metadata-Version: 1.1
Name: meow
Version: 0.3.1
Summary: meow is an editor-agnostic markdown/reST live preview server.
Home-page: https://github.com/hhatto/meow
Author: Hideo Hattori
Author-email: hhatto.jp@gmail.com
License: MIT
Keywords: markdown,reStructuredText,pygments,preview,bottle,github
Platform: any
Classifier: Development Status :: 3 - Alpha
Classifier: License :: OSI Approved :: MIT License
Classifier: Intended Audience :: Developers
Classifier: Intended Audience :: End Users/Desktop
Classifier: Operating System :: OS Independent
Classifier: Programming Language :: Python
Classifier: Programming Language :: Python :: 2
Classifier: Programming Language :: Python :: 3
Classifier: Topic :: Utilities
